excel2moodle/__init__.py
excel2moodle/__main__.py
excel2moodle/logger.py
excel2moodle/core/__init__.py
excel2moodle/core/bullets.py
excel2moodle/core/category.py
excel2moodle/core/dataStructure.py
excel2moodle/core/etHelpers.py
excel2moodle/core/exceptions.py
excel2moodle/core/globals.py
excel2moodle/core/parser.py
excel2moodle/core/question.py
excel2moodle/core/settings.py
excel2moodle/core/stringHelpers.py
excel2moodle/core/validator.py
excel2moodle/extra/__init__.py
excel2moodle/extra/equationChecker.py
excel2moodle/extra/scriptCaller.py
excel2moodle/extra/updateQuery.py
excel2moodle/extra/variableGenerator.py
excel2moodle/question_types/__init__.py
excel2moodle/question_types/cloze.py
excel2moodle/question_types/mc.py
excel2moodle/question_types/nf.py
excel2moodle/question_types/nfm.py
excel2moodle/ui/UI_equationChecker.py
excel2moodle/ui/UI_exportSettingsDialog.py
excel2moodle/ui/UI_mainWindow.py
excel2moodle/ui/UI_updateDlg.py
excel2moodle/ui/UI_variableGenerator.py
excel2moodle/ui/UI_variantDialog.py
excel2moodle/ui/__init__.py
excel2moodle/ui/appUi.py
excel2moodle/ui/dialogs.py
excel2moodle/ui/treewidget.py
excel2moodle-0.9.3.dist-info/licenses/LICENSE
excel2moodle-0.9.3.dist-info/METADATA
excel2moodle-0.9.3.dist-info/WHEEL
excel2moodle-0.9.3.dist-info/entry_points.txt
excel2moodle-0.9.3.dist-info/top_level.txt
excel2moodle-0.9.3.dist-info/RECORD
