Metadata-Version: 2.4
Name: excel2moodle
Version: 0.9.3
Summary: A package for converting questions from a spreadsheet, to valid moodle-xml
Author: Jakob Bosse
License-Expression: GPL-3.0-or-later
Project-URL: Repository, https://gitlab.com/jbosse3/excel2moodle.git
Project-URL: Documentation, https://jbosse3.gitlab.io/excel2moodle
Keywords: moodle,XML,teaching,question,converter,open educational Ressource
Classifier: Programming Language :: Python :: 3
Classifier: Operating System :: OS Independent
Requires-Python: >=3.10
License-File: LICENSE
Requires-Dist: pandas>=2.1.3
Requires-Dist: lxml>=5.4.0
Requires-Dist: asteval>=1.0.6
Requires-Dist: python-calamine>=0.3.2
Requires-Dist: pyside6-essentials>=6.8.0
Requires-Dist: pyyaml>=6.0.2
Requires-Dist: matplotlib>=3.10.7
Dynamic: license-file
